{
  "generated_at": "2026-07-14T09:14:26.687958+00:00",
  "total": 125,
  "fresh_count": 107,
  "stale_count": 10,
  "dead_count": 8,
  "health_score": 85.6,
  "fresh": [
    {
      "file": "arpa_e_projects_auto.js",
      "label": "ARPA-E",
      "status": "fresh",
      "size_bytes": 125690,
      "cadence_days": 14,
      "last_updated": "2026-07-14T08:57:31+00:00",
      "age_hours": 0.3
    },
    {
      "file": "arxiv_papers_auto.js",
      "label": "arXiv Papers",
      "status": "fresh",
      "size_bytes": 9964,
      "cadence_days": 3,
      "last_updated": "2026-07-14T08:56:54+00:00",
      "age_hours": 0.3
    },
    {
      "file": "basket_prices_auto.json",
      "label": "Basket Prices",
      "status": "fresh",
      "size_bytes": 19159,
      "cadence_days": 14,
      "last_updated": "2026-07-14T09:11:07.635062+00:00",
      "age_hours": 0.1
    },
    {
      "file": "bill_of_lading_auto.js",
      "label": "Bill of Lading (Supply Chain)",
      "status": "fresh",
      "size_bytes": 9143,
      "cadence_days": 7,
      "last_updated": "2026-07-12T11:00:48+00:00",
      "age_hours": 46.2
    },
    {
      "file": "bill_of_lading_auto.json",
      "label": "Bill Of Lading",
      "status": "fresh",
      "size_bytes": 13028,
      "cadence_days": 14,
      "last_updated": "2026-07-12T11:00:48+00:00",
      "age_hours": 46.2
    },
    {
      "file": "budget_signals_auto.js",
      "label": "Budget Signals",
      "status": "fresh",
      "size_bytes": 3172,
      "cadence_days": 7,
      "last_updated": "2026-07-14T08:15:31+00:00",
      "age_hours": 1.0
    },
    {
      "file": "budget_signals_auto.json",
      "label": "Budget Signals",
      "status": "fresh",
      "size_bytes": 3059,
      "cadence_days": 14,
      "last_updated": "2026-07-14T09:11:07.635062+00:00",
      "age_hours": 0.1
    },
    {
      "file": "clinical_trials_auto.js",
      "label": "Clinical Trials",
      "status": "fresh",
      "size_bytes": 11818,
      "cadence_days": 3,
      "last_updated": "2026-07-14T08:56:58+00:00",
      "age_hours": 0.3
    },
    {
      "file": "comp_sets_auto.js",
      "label": "Comp Sets",
      "status": "fresh",
      "size_bytes": 6109704,
      "cadence_days": 14,
      "last_updated": "2026-07-12T00:00:00+00:00",
      "age_hours": 57.2
    },
    {
      "file": "comp_sets_auto.json",
      "label": "Comp Sets",
      "status": "fresh",
      "size_bytes": 6109518,
      "cadence_days": 14,
      "last_updated": "2026-07-14T09:11:07.717062+00:00",
      "age_hours": 0.1
    },
    {
      "file": "conference_presence_auto.json",
      "label": "Conference Presence",
      "status": "fresh",
      "size_bytes": 28956,
      "cadence_days": 14,
      "last_updated": "2026-07-14T09:11:07.719062+00:00",
      "age_hours": 0.1
    },
    {
      "file": "congress_bills_auto.js",
      "label": "Congress Bills",
      "status": "fresh",
      "size_bytes": 5675,
      "cadence_days": 3,
      "last_updated": "2026-07-14T09:11:08.649732+00:00",
      "age_hours": 0.1
    },
    {
      "file": "congress_bills_auto.json",
      "label": "Congress Bills",
      "status": "fresh",
      "size_bytes": 5610,
      "cadence_days": 14,
      "last_updated": "2026-07-14T09:11:08.649786+00:00",
      "age_hours": 0.1
    },
    {
      "file": "contractor_readiness_auto.js",
      "label": "Contractor Readiness",
      "status": "fresh",
      "size_bytes": 76867,
      "cadence_days": 7,
      "last_updated": "2026-07-14T08:15:31+00:00",
      "age_hours": 1.0
    },
    {
      "file": "contractor_readiness_auto.json",
      "label": "Contractor Readiness",
      "status": "fresh",
      "size_bytes": 76690,
      "cadence_days": 14,
      "last_updated": "2026-07-14T09:11:07.719062+00:00",
      "age_hours": 0.1
    },
    {
      "file": "daily_digest.json",
      "label": "Frontier Daily",
      "status": "fresh",
      "size_bytes": 6958,
      "cadence_days": 1,
      "last_updated": "2026-07-14T09:11:07.719062+00:00",
      "age_hours": 0.1
    },
    {
      "file": "darpa_programs_auto.json",
      "label": "Darpa Programs",
      "status": "fresh",
      "size_bytes": 640133,
      "cadence_days": 14,
      "last_updated": "2026-07-14T09:11:07.721062+00:00",
      "age_hours": 0.1
    },
    {
      "file": "deals_auto.json",
      "label": "Deals",
      "status": "fresh",
      "size_bytes": 50828,
      "cadence_days": 14,
      "last_updated": "2026-07-14T09:11:07.721062+00:00",
      "age_hours": 0.1
    },
    {
      "file": "deception_scores_auto.js",
      "label": "Deception Detector (Skill)",
      "status": "fresh",
      "size_bytes": 6436,
      "cadence_days": 7,
      "last_updated": "2026-07-12T11:00:52+00:00",
      "age_hours": 46.2
    },
    {
      "file": "deception_scores_auto.json",
      "label": "Deception Scores",
      "status": "fresh",
      "size_bytes": 7459,
      "cadence_days": 14,
      "last_updated": "2026-07-12T11:00:52+00:00",
      "age_hours": 46.2
    },
    {
      "file": "demand_signals_auto.js",
      "label": "Demand Signals",
      "status": "fresh",
      "size_bytes": 152625,
      "cadence_days": 3,
      "last_updated": "2026-07-14T08:56:28+00:00",
      "age_hours": 0.3
    },
    {
      "file": "demand_signals_auto.json",
      "label": "Demand Signals",
      "status": "fresh",
      "size_bytes": 165603,
      "cadence_days": 14,
      "last_updated": "2026-07-14T09:11:08.650014+00:00",
      "age_hours": 0.1
    },
    {
      "file": "diffbot_enrichment_auto.js",
      "label": "Diffbot Enrichment",
      "status": "fresh",
      "size_bytes": 53346,
      "cadence_days": 7,
      "last_updated": "2026-07-14T09:10:25+00:00",
      "age_hours": 0.1
    },
    {
      "file": "discovery_queue_auto.js",
      "label": "Discovery Queue",
      "status": "fresh",
      "size_bytes": 34451,
      "cadence_days": 14,
      "last_updated": "2026-07-12T00:00:00+00:00",
      "age_hours": 57.2
    },
    {
      "file": "discovery_queue_auto.json",
      "label": "Discovery Queue",
      "status": "fresh",
      "size_bytes": 34241,
      "cadence_days": 14,
      "last_updated": "2026-07-14T09:11:07.723063+00:00",
      "age_hours": 0.1
    },
    {
      "file": "doe_programs_auto.js",
      "label": "DOE Programs",
      "status": "fresh",
      "size_bytes": 4026,
      "cadence_days": 14,
      "last_updated": "2026-07-14T08:56:32+00:00",
      "age_hours": 0.3
    },
    {
      "file": "dsca_fms_auto.js",
      "label": "DSCA Arms Sales",
      "status": "fresh",
      "size_bytes": 6080,
      "cadence_days": 7,
      "last_updated": "2026-07-12T11:00:45+00:00",
      "age_hours": 46.2
    },
    {
      "file": "dsca_fms_auto.json",
      "label": "Dsca Fms",
      "status": "fresh",
      "size_bytes": 7539,
      "cadence_days": 14,
      "last_updated": "2026-07-12T11:00:45+00:00",
      "age_hours": 46.2
    },
    {
      "file": "earnings_signals_auto.json",
      "label": "Earnings Signals",
      "status": "fresh",
      "size_bytes": 18172,
      "cadence_days": 14,
      "last_updated": "2026-07-14T09:13:14.175699+00:00",
      "age_hours": 0.0
    },
    {
      "file": "exec_moves_auto.json",
      "label": "Exec Moves",
      "status": "fresh",
      "size_bytes": 138251,
      "cadence_days": 14,
      "last_updated": "2026-07-14T09:14:08.485182+00:00",
      "age_hours": 0.0
    },
    {
      "file": "expert_takes_auto.js",
      "label": "Expert Takes",
      "status": "fresh",
      "size_bytes": 3096,
      "cadence_days": 3,
      "last_updated": "2026-07-14T08:15:31+00:00",
      "age_hours": 1.0
    },
    {
      "file": "expert_takes_auto.json",
      "label": "Expert Takes",
      "status": "fresh",
      "size_bytes": 2942,
      "cadence_days": 14,
      "last_updated": "2026-07-14T08:15:30+00:00",
      "age_hours": 1.0
    },
    {
      "file": "export_controls_auto.js",
      "label": "Export Controls",
      "status": "fresh",
      "size_bytes": 512,
      "cadence_days": 14,
      "last_updated": "2026-07-14T09:14:26+00:00",
      "age_hours": 0.0
    },
    {
      "file": "faa_certification_auto.js",
      "label": "FAA Type Certs",
      "status": "fresh",
      "size_bytes": 11809,
      "cadence_days": 7,
      "last_updated": "2026-07-14T09:11:08.650548+00:00",
      "age_hours": 0.1
    },
    {
      "file": "faa_certification_auto.json",
      "label": "Faa Certification",
      "status": "fresh",
      "size_bytes": 11741,
      "cadence_days": 14,
      "last_updated": "2026-07-14T09:11:08.650618+00:00",
      "age_hours": 0.1
    },
    {
      "file": "fcc_licenses_auto.js",
      "label": "FCC Licenses (ULS/ELS)",
      "status": "fresh",
      "size_bytes": 5069,
      "cadence_days": 7,
      "last_updated": "2026-07-12T11:00:45+00:00",
      "age_hours": 46.2
    },
    {
      "file": "fcc_licenses_auto.json",
      "label": "Fcc Licenses",
      "status": "fresh",
      "size_bytes": 5862,
      "cadence_days": 14,
      "last_updated": "2026-07-12T11:00:45+00:00",
      "age_hours": 46.2
    },
    {
      "file": "federal_grants_auto.json",
      "label": "Federal Grants",
      "status": "fresh",
      "size_bytes": 99495,
      "cadence_days": 14,
      "last_updated": "2026-07-14T09:13:43.100162+00:00",
      "age_hours": 0.0
    },
    {
      "file": "federal_register_auto.js",
      "label": "Federal Register",
      "status": "fresh",
      "size_bytes": 6996,
      "cadence_days": 2,
      "last_updated": "2026-07-14T08:56:31+00:00",
      "age_hours": 0.3
    },
    {
      "file": "form_d_filings_auto.js",
      "label": "Form D Filings",
      "status": "fresh",
      "size_bytes": 11316,
      "cadence_days": 14,
      "last_updated": "2026-07-14T09:14:23+00:00",
      "age_hours": 0.0
    },
    {
      "file": "form_d_filings_auto.json",
      "label": "Form D Filings",
      "status": "fresh",
      "size_bytes": 11123,
      "cadence_days": 14,
      "last_updated": "2026-07-14T09:14:23+00:00",
      "age_hours": 0.0
    },
    {
      "file": "founder_mafias_auto.js",
      "label": "Founder Mafias",
      "status": "fresh",
      "size_bytes": 11295,
      "cadence_days": 14,
      "last_updated": "2026-07-14T08:15:31+00:00",
      "age_hours": 1.0
    },
    {
      "file": "founder_mafias_auto.json",
      "label": "Founder Mafias",
      "status": "fresh",
      "size_bytes": 11133,
      "cadence_days": 14,
      "last_updated": "2026-07-14T09:11:07.730062+00:00",
      "age_hours": 0.1
    },
    {
      "file": "fund_intelligence_auto.js",
      "label": "Fund Intelligence",
      "status": "fresh",
      "size_bytes": 5380,
      "cadence_days": 7,
      "last_updated": "2026-07-14T08:15:31+00:00",
      "age_hours": 1.0
    },
    {
      "file": "fund_intelligence_auto.json",
      "label": "Fund Intelligence",
      "status": "fresh",
      "size_bytes": 5209,
      "cadence_days": 14,
      "last_updated": "2026-07-14T08:15:30+00:00",
      "age_hours": 1.0
    },
    {
      "file": "funding_tracker_auto.json",
      "label": "Funding Tracker",
      "status": "fresh",
      "size_bytes": 37237,
      "cadence_days": 14,
      "last_updated": "2026-07-14T09:11:07.730062+00:00",
      "age_hours": 0.1
    },
    {
      "file": "github_signals_auto.json",
      "label": "Github Signals",
      "status": "fresh",
      "size_bytes": 14534,
      "cadence_days": 14,
      "last_updated": "2026-07-14T09:11:08.651062+00:00",
      "age_hours": 0.1
    },
    {
      "file": "gov_contracts_auto.js",
      "label": "Gov Contracts",
      "status": "fresh",
      "size_bytes": 6036,
      "cadence_days": 2,
      "last_updated": "2026-07-14T08:14:30+00:00",
      "age_hours": 1.0
    },
    {
      "file": "gov_demand_summary_auto.js",
      "label": "Gov Demand Summary",
      "status": "fresh",
      "size_bytes": 7055,
      "cadence_days": 7,
      "last_updated": "2026-07-14T08:15:31+00:00",
      "age_hours": 1.0
    },
    {
      "file": "gov_demand_summary_auto.json",
      "label": "Gov Demand Summary",
      "status": "fresh",
      "size_bytes": 6953,
      "cadence_days": 14,
      "last_updated": "2026-07-14T08:15:30+00:00",
      "age_hours": 1.0
    },
    {
      "file": "growth_signals_auto.json",
      "label": "Growth Signals",
      "status": "fresh",
      "size_bytes": 10517,
      "cadence_days": 14,
      "last_updated": "2026-07-14T09:11:07.751062+00:00",
      "age_hours": 0.1
    },
    {
      "file": "h1b_lca_auto.js",
      "label": "H-1B LCA Hiring",
      "status": "fresh",
      "size_bytes": 10992,
      "cadence_days": 30,
      "last_updated": "2026-07-12T11:00:45+00:00",
      "age_hours": 46.2
    },
    {
      "file": "h1b_lca_auto.json",
      "label": "H1B Lca",
      "status": "fresh",
      "size_bytes": 15974,
      "cadence_days": 14,
      "last_updated": "2026-07-12T11:00:45+00:00",
      "age_hours": 46.2
    },
    {
      "file": "hackernews_buzz_auto.js",
      "label": "HN Buzz",
      "status": "fresh",
      "size_bytes": 6048,
      "cadence_days": 3,
      "last_updated": "2026-07-14T08:56:45+00:00",
      "age_hours": 0.3
    },
    {
      "file": "headcount_estimates_auto.js",
      "label": "Headcount Estimates",
      "status": "fresh",
      "size_bytes": 22864,
      "cadence_days": 7,
      "last_updated": "2026-07-14T08:15:29+00:00",
      "age_hours": 1.0
    },
    {
      "file": "headcount_estimates_auto.json",
      "label": "Headcount Estimates",
      "status": "fresh",
      "size_bytes": 24157,
      "cadence_days": 14,
      "last_updated": "2026-07-14T09:11:07.752063+00:00",
      "age_hours": 0.1
    },
    {
      "file": "innovator_scores_auto.json",
      "label": "Innovator Scores",
      "status": "fresh",
      "size_bytes": 796548,
      "cadence_days": 14,
      "last_updated": "2026-07-14T09:11:07.754062+00:00",
      "age_hours": 0.1
    },
    {
      "file": "interconnection_queue_auto.js",
      "label": "Power Grid (FERC/ISO)",
      "status": "fresh",
      "size_bytes": 5758,
      "cadence_days": 7,
      "last_updated": "2026-07-12T09:48:50+00:00",
      "age_hours": 47.4
    },
    {
      "file": "interconnection_queue_auto.json",
      "label": "Interconnection Queue",
      "status": "fresh",
      "size_bytes": 6972,
      "cadence_days": 14,
      "last_updated": "2026-07-12T09:48:50+00:00",
      "age_hours": 47.4
    },
    {
      "file": "ipo_pipeline_auto.json",
      "label": "Ipo Pipeline",
      "status": "fresh",
      "size_bytes": 2303,
      "cadence_days": 14,
      "last_updated": "2026-07-14T09:11:07.755063+00:00",
      "age_hours": 0.1
    },
    {
      "file": "jobs_auto.js",
      "label": "Jobs Feed",
      "status": "fresh",
      "size_bytes": 3487118,
      "cadence_days": 1,
      "last_updated": "2026-07-14T08:12:24+00:00",
      "age_hours": 1.0
    },
    {
      "file": "launch_manifest_auto.json",
      "label": "Launch Manifest",
      "status": "fresh",
      "size_bytes": 18348,
      "cadence_days": 14,
      "last_updated": "2026-07-14T09:12:06.737097+00:00",
      "age_hours": 0.0
    },
    {
      "file": "linkedin_headcount_auto.json",
      "label": "LinkedIn Headcount",
      "status": "fresh",
      "size_bytes": 140095,
      "cadence_days": 7,
      "last_updated": "2026-07-14T09:11:07.770062+00:00",
      "age_hours": 0.1
    },
    {
      "file": "lobbying_auto.js",
      "label": "Senate Lobbying",
      "status": "fresh",
      "size_bytes": 9192,
      "cadence_days": 30,
      "last_updated": "2026-07-12T11:00:47+00:00",
      "age_hours": 46.2
    },
    {
      "file": "lobbying_auto.json",
      "label": "Lobbying",
      "status": "fresh",
      "size_bytes": 12981,
      "cadence_days": 14,
      "last_updated": "2026-07-12T11:00:47+00:00",
      "age_hours": 46.2
    },
    {
      "file": "ma_comps_auto.js",
      "label": "M&A Comps",
      "status": "fresh",
      "size_bytes": 516,
      "cadence_days": 14,
      "last_updated": "2026-07-11T08:03:25+00:00",
      "age_hours": 73.2
    },
    {
      "file": "nasa_projects_auto.js",
      "label": "NASA Projects",
      "status": "fresh",
      "size_bytes": 6020,
      "cadence_days": 7,
      "last_updated": "2026-07-14T08:57:52+00:00",
      "age_hours": 0.3
    },
    {
      "file": "network_graph_auto.js",
      "label": "Network Graph",
      "status": "fresh",
      "size_bytes": 235710,
      "cadence_days": 14,
      "last_updated": "2026-07-14T08:15:31+00:00",
      "age_hours": 1.0
    },
    {
      "file": "network_graph_auto.json",
      "label": "Network Graph",
      "status": "fresh",
      "size_bytes": 235522,
      "cadence_days": 14,
      "last_updated": "2026-07-14T09:11:07.773062+00:00",
      "age_hours": 0.1
    },
    {
      "file": "news_signals_auto.js",
      "label": "News Feed",
      "status": "fresh",
      "size_bytes": 7559,
      "cadence_days": 1,
      "last_updated": "2026-07-14T00:00:00+00:00",
      "age_hours": 9.2
    },
    {
      "file": "newsletter_signals_auto.json",
      "label": "Newsletter Signals",
      "status": "fresh",
      "size_bytes": 26679,
      "cadence_days": 14,
      "last_updated": "2026-07-14T09:11:07.774062+00:00",
      "age_hours": 0.1
    },
    {
      "file": "nih_grants_auto.js",
      "label": "NIH Grants",
      "status": "fresh",
      "size_bytes": 205115,
      "cadence_days": 7,
      "last_updated": "2026-07-14T08:56:39+00:00",
      "age_hours": 0.3
    },
    {
      "file": "nrc_licensing_auto.js",
      "label": "NRC Licensing",
      "status": "fresh",
      "size_bytes": 7262,
      "cadence_days": 3,
      "last_updated": "2026-07-14T09:11:08.655719+00:00",
      "age_hours": 0.1
    },
    {
      "file": "nrc_licensing_auto.json",
      "label": "Nrc Licensing",
      "status": "fresh",
      "size_bytes": 6205,
      "cadence_days": 14,
      "last_updated": "2026-07-14T09:11:08.655772+00:00",
      "age_hours": 0.1
    },
    {
      "file": "nsf_awards_auto.js",
      "label": "NSF Awards",
      "status": "fresh",
      "size_bytes": 9778,
      "cadence_days": 7,
      "last_updated": "2026-07-14T08:56:43+00:00",
      "age_hours": 0.3
    },
    {
      "file": "patent_intel_auto.js",
      "label": "Patent Intel",
      "status": "fresh",
      "size_bytes": 45202,
      "cadence_days": 7,
      "last_updated": "2026-07-12T09:48:24+00:00",
      "age_hours": 47.4
    },
    {
      "file": "patent_velocity_auto.json",
      "label": "Patent Velocity",
      "status": "fresh",
      "size_bytes": 34371,
      "cadence_days": 14,
      "last_updated": "2026-07-14T09:11:07.783062+00:00",
      "age_hours": 0.1
    },
    {
      "file": "podcast_mentions_auto.json",
      "label": "Podcast Mentions",
      "status": "fresh",
      "size_bytes": 200874,
      "cadence_days": 14,
      "last_updated": "2026-07-14T09:11:08.656031+00:00",
      "age_hours": 0.1
    },
    {
      "file": "podcast_signals_auto.json",
      "label": "Podcast Signals",
      "status": "fresh",
      "size_bytes": 94067,
      "cadence_days": 14,
      "last_updated": "2026-07-14T09:11:07.785063+00:00",
      "age_hours": 0.1
    },
    {
      "file": "predictive_scores_auto.json",
      "label": "Predictive Scores",
      "status": "fresh",
      "size_bytes": 997441,
      "cadence_days": 14,
      "last_updated": "2026-07-14T09:11:07.912063+00:00",
      "age_hours": 0.1
    },
    {
      "file": "press_releases_auto.js",
      "label": "Press Releases",
      "status": "fresh",
      "size_bytes": 1156,
      "cadence_days": 2,
      "last_updated": "2026-07-14T08:56:36+00:00",
      "age_hours": 0.3
    },
    {
      "file": "prime_supply_chain_auto.json",
      "label": "Prime Supply Chain",
      "status": "fresh",
      "size_bytes": 17119,
      "cadence_days": 14,
      "last_updated": "2026-07-14T09:12:04.821118+00:00",
      "age_hours": 0.0
    },
    {
      "file": "public_multiples_auto.js",
      "label": "Public Multiples",
      "status": "fresh",
      "size_bytes": 35621,
      "cadence_days": 14,
      "last_updated": "2026-07-14T00:00:00+00:00",
      "age_hours": 9.2
    },
    {
      "file": "public_multiples_auto.json",
      "label": "Public Multiples",
      "status": "fresh",
      "size_bytes": 35407,
      "cadence_days": 14,
      "last_updated": "2026-07-14T09:11:07.915063+00:00",
      "age_hours": 0.1
    },
    {
      "file": "reddit_mentions_auto.json",
      "label": "Reddit Mentions",
      "status": "fresh",
      "size_bytes": 316263,
      "cadence_days": 14,
      "last_updated": "2026-07-14T09:11:07.916063+00:00",
      "age_hours": 0.1
    },
    {
      "file": "revenue_intel_auto.json",
      "label": "Revenue Intel",
      "status": "fresh",
      "size_bytes": 9280,
      "cadence_days": 14,
      "last_updated": "2026-07-14T09:11:07.916063+00:00",
      "age_hours": 0.1
    },
    {
      "file": "sam_contracts_auto.js",
      "label": "SAM.gov",
      "status": "fresh",
      "size_bytes": 12898,
      "cadence_days": 2,
      "last_updated": "2026-07-14T08:56:50+00:00",
      "age_hours": 0.3
    },
    {
      "file": "sbir_awards_auto.json",
      "label": "Sbir Awards",
      "status": "fresh",
      "size_bytes": 162853,
      "cadence_days": 14,
      "last_updated": "2026-07-14T09:11:07.918063+00:00",
      "age_hours": 0.1
    },
    {
      "file": "sbir_topics_auto.js",
      "label": "SBIR Topics",
      "status": "fresh",
      "size_bytes": 23508,
      "cadence_days": 3,
      "last_updated": "2026-07-14T09:14:26+00:00",
      "age_hours": 0.0
    },
    {
      "file": "sbir_topics_auto.json",
      "label": "Sbir Topics",
      "status": "fresh",
      "size_bytes": 5267,
      "cadence_days": 14,
      "last_updated": "2026-07-14T09:11:08.656782+00:00",
      "age_hours": 0.1
    },
    {
      "file": "scout_briefing_auto.js",
      "label": "Scout Briefing",
      "status": "fresh",
      "size_bytes": 13458,
      "cadence_days": 14,
      "last_updated": "2026-07-12T00:00:00+00:00",
      "age_hours": 57.2
    },
    {
      "file": "scout_briefing_auto.json",
      "label": "Scout Briefing",
      "status": "fresh",
      "size_bytes": 13252,
      "cadence_days": 14,
      "last_updated": "2026-07-14T09:11:07.919063+00:00",
      "age_hours": 0.1
    },
    {
      "file": "sec_filings_auto.js",
      "label": "SEC Filings",
      "status": "fresh",
      "size_bytes": 7121,
      "cadence_days": 2,
      "last_updated": "2026-07-14T08:14:26+00:00",
      "age_hours": 1.0
    },
    {
      "file": "secondary_market_auto.json",
      "label": "Secondary Market",
      "status": "fresh",
      "size_bytes": 13489,
      "cadence_days": 14,
      "last_updated": "2026-07-14T09:11:07.921063+00:00",
      "age_hours": 0.1
    },
    {
      "file": "sector_momentum_auto.json",
      "label": "Sector Momentum",
      "status": "fresh",
      "size_bytes": 6616,
      "cadence_days": 14,
      "last_updated": "2026-07-14T09:11:07.921063+00:00",
      "age_hours": 0.1
    },
    {
      "file": "spinouts_auto.json",
      "label": "Spinouts",
      "status": "fresh",
      "size_bytes": 14248,
      "cadence_days": 14,
      "last_updated": "2026-07-14T09:14:08.332355+00:00",
      "age_hours": 0.0
    },
    {
      "file": "state_puct_dockets_auto.js",
      "label": "State PUC Dockets",
      "status": "fresh",
      "size_bytes": 5383,
      "cadence_days": 7,
      "last_updated": "2026-07-12T11:00:48+00:00",
      "age_hours": 46.2
    },
    {
      "file": "state_puct_dockets_auto.json",
      "label": "State Puct Dockets",
      "status": "fresh",
      "size_bytes": 6388,
      "cadence_days": 14,
      "last_updated": "2026-07-12T11:00:48+00:00",
      "age_hours": 46.2
    },
    {
      "file": "stocks_auto.js",
      "label": "Stock Prices",
      "status": "fresh",
      "size_bytes": 32223,
      "cadence_days": 1,
      "last_updated": "2026-07-14T08:12:58+00:00",
      "age_hours": 1.0
    },
    {
      "file": "twitter_signals_auto.json",
      "label": "X / Twitter Signals",
      "status": "fresh",
      "size_bytes": 56493,
      "cadence_days": 3,
      "last_updated": "2026-07-14T09:11:08.656945+00:00",
      "age_hours": 0.1
    },
    {
      "file": "valuation_benchmarks_auto.json",
      "label": "Valuation Benchmarks",
      "status": "fresh",
      "size_bytes": 55434,
      "cadence_days": 14,
      "last_updated": "2026-07-14T09:11:07.922063+00:00",
      "age_hours": 0.1
    },
    {
      "file": "water_permits_auto.js",
      "label": "Water Permits",
      "status": "fresh",
      "size_bytes": 5121,
      "cadence_days": 7,
      "last_updated": "2026-07-12T11:00:52+00:00",
      "age_hours": 46.2
    },
    {
      "file": "water_permits_auto.json",
      "label": "Water Permits",
      "status": "fresh",
      "size_bytes": 6001,
      "cadence_days": 14,
      "last_updated": "2026-07-12T11:00:52+00:00",
      "age_hours": 46.2
    },
    {
      "file": "website_changes_auto.js",
      "label": "Website Changes (Wayback)",
      "status": "fresh",
      "size_bytes": 68976,
      "cadence_days": 7,
      "last_updated": "2026-07-12T11:00:34+00:00",
      "age_hours": 46.2
    },
    {
      "file": "website_changes_auto.json",
      "label": "Website Changes",
      "status": "fresh",
      "size_bytes": 92887,
      "cadence_days": 14,
      "last_updated": "2026-07-12T11:00:34+00:00",
      "age_hours": 46.2
    },
    {
      "file": "youtube_mentions_auto.js",
      "label": "Corporate Mentions (YouTube)",
      "status": "fresh",
      "size_bytes": 3370,
      "cadence_days": 7,
      "last_updated": "2026-07-12T11:00:47+00:00",
      "age_hours": 46.2
    },
    {
      "file": "youtube_mentions_auto.json",
      "label": "Youtube Mentions",
      "status": "fresh",
      "size_bytes": 3844,
      "cadence_days": 14,
      "last_updated": "2026-07-12T11:00:47+00:00",
      "age_hours": 46.2
    }
  ],
  "stale": [
    {
      "file": "darpa_programs_auto.js",
      "label": "Darpa Programs",
      "status": "stale",
      "size_bytes": 640339,
      "cadence_days": 14,
      "last_updated": "2026-04-27T00:00:00+00:00",
      "age_hours": 1881.2
    },
    {
      "file": "factory_watch_auto.js",
      "label": "Factory Watch",
      "status": "stale",
      "size_bytes": 90016,
      "cadence_days": 14,
      "last_updated": "2026-04-23T05:07:36+00:00",
      "age_hours": 1972.1
    },
    {
      "file": "factory_watch_auto.json",
      "label": "Factory Watch",
      "status": "stale",
      "size_bytes": 89746,
      "cadence_days": 14,
      "last_updated": "2026-04-23T05:07:36+00:00",
      "age_hours": 1972.1
    },
    {
      "file": "fda_actions_auto.js",
      "label": "FDA Actions",
      "status": "stale",
      "size_bytes": 20278,
      "cadence_days": 7,
      "last_updated": "2026-05-12T00:00:00+00:00",
      "age_hours": 1521.2
    },
    {
      "file": "field_notes_auto.js",
      "label": "Field Notes",
      "status": "stale",
      "size_bytes": 6618,
      "cadence_days": 7,
      "last_updated": "2026-04-21T07:03:48+00:00",
      "age_hours": 2018.2
    },
    {
      "file": "github_releases_auto.js",
      "label": "GitHub Releases",
      "status": "stale",
      "size_bytes": 3808,
      "cadence_days": 7,
      "last_updated": "2026-04-23T08:22:00+00:00",
      "age_hours": 1968.9
    },
    {
      "file": "insider_transactions_auto.js",
      "label": "Insider Trades",
      "status": "stale",
      "size_bytes": 5305,
      "cadence_days": 7,
      "last_updated": "2026-04-23T08:19:43+00:00",
      "age_hours": 1968.9
    },
    {
      "file": "product_launches_auto.js",
      "label": "Product Launches",
      "status": "stale",
      "size_bytes": 14291,
      "cadence_days": 7,
      "last_updated": "2026-04-19T09:41:20+00:00",
      "age_hours": 2063.6
    },
    {
      "file": "trademarks_auto.js",
      "label": "Trademarks",
      "status": "stale",
      "size_bytes": 7408,
      "cadence_days": 14,
      "last_updated": "2026-04-23T04:54:49+00:00",
      "age_hours": 1972.3
    },
    {
      "file": "trademarks_auto.json",
      "label": "Trademarks",
      "status": "stale",
      "size_bytes": 7177,
      "cadence_days": 14,
      "last_updated": "2026-04-23T04:54:49+00:00",
      "age_hours": 1972.3
    }
  ],
  "dead": [
    {
      "file": "export_controls_auto.json",
      "label": "Export Controls",
      "status": "dead",
      "size_bytes": 289,
      "cadence_days": 14,
      "last_updated": "2026-07-14T09:14:26+00:00",
      "age_hours": 0.0
    },
    {
      "file": "field_notes_auto.json",
      "label": "Field Notes",
      "status": "dead",
      "size_bytes": 2,
      "cadence_days": 14,
      "last_updated": "2026-07-14T09:11:07.728062+00:00",
      "age_hours": 0.1
    },
    {
      "file": "founder_insights_auto.js",
      "label": "Founder Insights",
      "status": "dead",
      "size_bytes": 425,
      "cadence_days": 14,
      "last_updated": "2026-07-12T00:00:00+00:00",
      "age_hours": 57.2
    },
    {
      "file": "founder_insights_auto.json",
      "label": "Founder Insights",
      "status": "dead",
      "size_bytes": 211,
      "cadence_days": 14,
      "last_updated": "2026-07-14T09:11:07.729063+00:00",
      "age_hours": 0.1
    },
    {
      "file": "funding_feed_auto.json",
      "label": "Funding Feed",
      "status": "dead",
      "size_bytes": 336,
      "cadence_days": 14,
      "last_updated": "2026-07-14T09:11:08.650954+00:00",
      "age_hours": 0.1
    },
    {
      "file": "ma_comps_auto.json",
      "label": "Ma Comps",
      "status": "dead",
      "size_bytes": 2,
      "cadence_days": 14,
      "last_updated": "2026-07-14T09:11:07.770062+00:00",
      "age_hours": 0.1
    },
    {
      "file": "sbir_awards_auto.js",
      "label": "SBIR Awards",
      "status": "dead",
      "size_bytes": 200,
      "cadence_days": 7,
      "last_updated": "2026-04-15T00:00:00+00:00",
      "age_hours": 2169.2
    },
    {
      "file": "trade_data_auto.js",
      "label": "Trade Data",
      "status": "dead",
      "size_bytes": 165,
      "cadence_days": 7,
      "last_updated": "2026-07-14T08:56:46+00:00",
      "age_hours": 0.3
    }
  ]
}