{
  "totalMarketCap": "$0.0B",
  "companiesTracked": 32,
  "sectorPerformance": {
    "ai": {
      "gainers": 1,
      "losers": 0,
      "avg_change": 16.42,
      "count": 1
    },
    "space": {
      "gainers": 5,
      "losers": 2,
      "avg_change": 7.08,
      "count": 7
    },
    "autonomous": {
      "gainers": 2,
      "losers": 5,
      "avg_change": -1.58,
      "count": 7
    },
    "nuclear": {
      "gainers": 0,
      "losers": 3,
      "avg_change": -7.59,
      "count": 3
    },
    "climate": {
      "gainers": 1,
      "losers": 2,
      "avg_change": -1.02,
      "count": 3
    },
    "quantum": {
      "gainers": 1,
      "losers": 2,
      "avg_change": -1.53,
      "count": 3
    },
    "biotech": {
      "gainers": 0,
      "losers": 3,
      "avg_change": -4.9,
      "count": 3
    },
    "transportation": {
      "gainers": 1,
      "losers": 1,
      "avg_change": -0.24,
      "count": 2
    },
    "chips": {
      "gainers": 2,
      "losers": 1,
      "avg_change": 1.23,
      "count": 3
    }
  },
  "topGainers": [
    [
      "ASTS",
      "AST SpaceMobile",
      19.75
    ],
    [
      "PLTR",
      "Palantir",
      16.42
    ],
    [
      "LUNR",
      "Intuitive Machines",
      13.29
    ],
    [
      "PL",
      "Planet Labs",
      10.98
    ],
    [
      "DRSHF",
      "DroneShield",
      10.61
    ]
  ],
  "topLosers": [
    [
      "ONT.L",
      "Oxford Nanopore Technologies",
      -8.49
    ],
    [
      "SMR",
      "NuScale Power",
      -8.68
    ],
    [
      "NNE",
      "Nano Nuclear Energy",
      -9.78
    ],
    [
      "SLDP",
      "Solid Power",
      -10.31
    ],
    [
      "ACHR",
      "Archer Aviation",
      -10.59
    ]
  ],
  "lastUpdated": "2026-03-06 18:53:27"
}