{
  "totalMarketCap": "$0.0B",
  "companiesTracked": 32,
  "sectorPerformance": {
    "ai": {
      "gainers": 1,
      "losers": 0,
      "avg_change": 8.81,
      "count": 1
    },
    "space": {
      "gainers": 5,
      "losers": 2,
      "avg_change": 8.24,
      "count": 7
    },
    "autonomous": {
      "gainers": 6,
      "losers": 1,
      "avg_change": 7.4,
      "count": 7
    },
    "nuclear": {
      "gainers": 3,
      "losers": 0,
      "avg_change": 15.8,
      "count": 3
    },
    "climate": {
      "gainers": 2,
      "losers": 1,
      "avg_change": -3.44,
      "count": 3
    },
    "quantum": {
      "gainers": 3,
      "losers": 0,
      "avg_change": 25.72,
      "count": 3
    },
    "biotech": {
      "gainers": 3,
      "losers": 0,
      "avg_change": 10.22,
      "count": 3
    },
    "transportation": {
      "gainers": 2,
      "losers": 0,
      "avg_change": 7.77,
      "count": 2
    },
    "chips": {
      "gainers": 3,
      "losers": 0,
      "avg_change": 7.19,
      "count": 3
    }
  },
  "topGainers": [
    [
      "IONQ",
      "IonQ",
      34.19
    ],
    [
      "QBTS",
      "D-Wave Quantum",
      27.4
    ],
    [
      "RKLB",
      "Rocket Lab",
      25.64
    ],
    [
      "SLDP",
      "Solid Power",
      22.57
    ],
    [
      "SMR",
      "NuScale Power",
      22.54
    ]
  ],
  "topLosers": [
    [
      "SATL",
      "Satellogic",
      0.55
    ],
    [
      "277810.KQ",
      "Rainbow Robotics",
      -0.33
    ],
    [
      "9348.T",
      "ispace",
      -4.69
    ],
    [
      "ASTS",
      "AST SpaceMobile",
      -6.1
    ],
    [
      "LNZA",
      "LanzaTech",
      -39.81
    ]
  ],
  "lastUpdated": "2026-04-21 13:53:38"
}