{
  "totalMarketCap": "$0.0B",
  "companiesTracked": 32,
  "sectorPerformance": {
    "ai": {
      "gainers": 1,
      "losers": 0,
      "avg_change": 0.07,
      "count": 1
    },
    "space": {
      "gainers": 7,
      "losers": 0,
      "avg_change": 21.77,
      "count": 7
    },
    "autonomous": {
      "gainers": 5,
      "losers": 2,
      "avg_change": 8.18,
      "count": 7
    },
    "nuclear": {
      "gainers": 3,
      "losers": 0,
      "avg_change": 9.25,
      "count": 3
    },
    "climate": {
      "gainers": 1,
      "losers": 2,
      "avg_change": -1.86,
      "count": 3
    },
    "quantum": {
      "gainers": 3,
      "losers": 0,
      "avg_change": 8.18,
      "count": 3
    },
    "biotech": {
      "gainers": 1,
      "losers": 2,
      "avg_change": -5.01,
      "count": 3
    },
    "transportation": {
      "gainers": 1,
      "losers": 1,
      "avg_change": 3.44,
      "count": 2
    },
    "chips": {
      "gainers": 2,
      "losers": 1,
      "avg_change": 11.11,
      "count": 3
    }
  },
  "topGainers": [
    [
      "RKLB",
      "Rocket Lab",
      49.26
    ],
    [
      "ASRHF",
      "Astroscale",
      39.19
    ],
    [
      "LUNR",
      "Intuitive Machines",
      29.4
    ],
    [
      "AMD",
      "AMD",
      26.19
    ],
    [
      "277810.KQ",
      "Rainbow Robotics",
      25.07
    ]
  ],
  "topLosers": [
    [
      "RXRX",
      "Recursion Pharmaceuticals",
      -6.53
    ],
    [
      "LNZA",
      "LanzaTech",
      -7.04
    ],
    [
      "TEM",
      "Tempus AI",
      -13.17
    ],
    [
      "DRSHF",
      "DroneShield",
      -14.06
    ],
    [
      "SLDP",
      "Solid Power",
      -14.53
    ]
  ],
  "lastUpdated": "2026-05-13 08:50:09"
}