{
  "totalMarketCap": "$0.0B",
  "companiesTracked": 32,
  "sectorPerformance": {
    "ai": {
      "gainers": 1,
      "losers": 0,
      "avg_change": 4.18,
      "count": 1
    },
    "space": {
      "gainers": 0,
      "losers": 7,
      "avg_change": -17.18,
      "count": 7
    },
    "autonomous": {
      "gainers": 1,
      "losers": 6,
      "avg_change": -6.94,
      "count": 7
    },
    "nuclear": {
      "gainers": 0,
      "losers": 3,
      "avg_change": -15.59,
      "count": 3
    },
    "climate": {
      "gainers": 0,
      "losers": 3,
      "avg_change": -8.25,
      "count": 3
    },
    "quantum": {
      "gainers": 0,
      "losers": 3,
      "avg_change": -19.55,
      "count": 3
    },
    "biotech": {
      "gainers": 0,
      "losers": 3,
      "avg_change": -11.69,
      "count": 3
    },
    "transportation": {
      "gainers": 0,
      "losers": 2,
      "avg_change": -4.75,
      "count": 2
    },
    "chips": {
      "gainers": 1,
      "losers": 2,
      "avg_change": -9.83,
      "count": 3
    }
  },
  "topGainers": [
    [
      "PLTR",
      "Palantir",
      4.18
    ],
    [
      "NVDA",
      "NVIDIA",
      2.28
    ],
    [
      "DRSHF",
      "DroneShield",
      0.63
    ],
    [
      "SLDP",
      "Solid Power",
      -2.08
    ],
    [
      "ONT.L",
      "Oxford Nanopore Technologies",
      -2.52
    ]
  ],
  "topLosers": [
    [
      "LUNR",
      "Intuitive Machines",
      -20.47
    ],
    [
      "IONQ",
      "IonQ",
      -21.6
    ],
    [
      "SATL",
      "Satellogic",
      -22.56
    ],
    [
      "ALAB",
      "Astera Labs",
      -23.41
    ],
    [
      "ASTS",
      "AST SpaceMobile",
      -25.54
    ]
  ],
  "lastUpdated": "2026-07-17 02:53:26"
}