{
  "totalMarketCap": "$0.0B",
  "companiesTracked": 32,
  "sectorPerformance": {
    "ai": {
      "gainers": 1,
      "losers": 0,
      "avg_change": 10.07,
      "count": 1
    },
    "space": {
      "gainers": 0,
      "losers": 7,
      "avg_change": -12.04,
      "count": 7
    },
    "autonomous": {
      "gainers": 3,
      "losers": 4,
      "avg_change": -4.38,
      "count": 7
    },
    "nuclear": {
      "gainers": 0,
      "losers": 3,
      "avg_change": -10.18,
      "count": 3
    },
    "climate": {
      "gainers": 0,
      "losers": 3,
      "avg_change": -11.55,
      "count": 3
    },
    "quantum": {
      "gainers": 0,
      "losers": 3,
      "avg_change": -12.74,
      "count": 3
    },
    "biotech": {
      "gainers": 2,
      "losers": 1,
      "avg_change": -2.6,
      "count": 3
    },
    "transportation": {
      "gainers": 0,
      "losers": 2,
      "avg_change": -6.96,
      "count": 2
    },
    "chips": {
      "gainers": 0,
      "losers": 3,
      "avg_change": -10.19,
      "count": 3
    }
  },
  "topGainers": [
    [
      "PLTR",
      "Palantir",
      10.07
    ],
    [
      "ACHR",
      "Archer Aviation",
      4.44
    ],
    [
      "RXRX",
      "Recursion Pharmaceuticals",
      2.72
    ],
    [
      "IDEAFORGE.NS",
      "ideaForge",
      1.51
    ],
    [
      "TEM",
      "Tempus AI",
      1.1
    ]
  ],
  "topLosers": [
    [
      "PL",
      "Planet Labs",
      -15.67
    ],
    [
      "LUNR",
      "Intuitive Machines",
      -15.99
    ],
    [
      "RKLB",
      "Rocket Lab",
      -16.94
    ],
    [
      "277810.KQ",
      "Rainbow Robotics",
      -17.44
    ],
    [
      "ALAB",
      "Astera Labs",
      -18.38
    ]
  ],
  "lastUpdated": "2026-07-08 14:22:16"
}