{
  "totalMarketCap": "$0.0B",
  "companiesTracked": 32,
  "sectorPerformance": {
    "ai": {
      "gainers": 1,
      "losers": 0,
      "avg_change": 16.14,
      "count": 1
    },
    "space": {
      "gainers": 0,
      "losers": 7,
      "avg_change": -11.01,
      "count": 7
    },
    "autonomous": {
      "gainers": 4,
      "losers": 3,
      "avg_change": -2.39,
      "count": 7
    },
    "nuclear": {
      "gainers": 0,
      "losers": 3,
      "avg_change": -11.12,
      "count": 3
    },
    "climate": {
      "gainers": 0,
      "losers": 3,
      "avg_change": -14.93,
      "count": 3
    },
    "quantum": {
      "gainers": 0,
      "losers": 3,
      "avg_change": -14.1,
      "count": 3
    },
    "biotech": {
      "gainers": 2,
      "losers": 1,
      "avg_change": -1.52,
      "count": 3
    },
    "transportation": {
      "gainers": 0,
      "losers": 2,
      "avg_change": -2.04,
      "count": 2
    },
    "chips": {
      "gainers": 1,
      "losers": 2,
      "avg_change": -6.45,
      "count": 3
    }
  },
  "topGainers": [
    [
      "PLTR",
      "Palantir",
      16.14
    ],
    [
      "ACHR",
      "Archer Aviation",
      5.34
    ],
    [
      "RXRX",
      "Recursion Pharmaceuticals",
      4.07
    ],
    [
      "TEM",
      "Tempus AI",
      3.05
    ],
    [
      "EVTL",
      "Vertical Aerospace",
      2.87
    ]
  ],
  "topLosers": [
    [
      "RKLB",
      "Rocket Lab",
      -14.9
    ],
    [
      "IONQ",
      "IonQ",
      -15.81
    ],
    [
      "ALAB",
      "Astera Labs",
      -16.03
    ],
    [
      "277810.KQ",
      "Rainbow Robotics",
      -17.44
    ],
    [
      "LNZA",
      "LanzaTech",
      -26.93
    ]
  ],
  "lastUpdated": "2026-07-08 08:35:01"
}